flowgo/__init__.py
flowgo-1.1.dist-info/LICENSE
flowgo-1.1.dist-info/METADATA
flowgo-1.1.dist-info/WHEEL
flowgo-1.1.dist-info/top_level.txt
flowgo-1.1.dist-info/RECORD
