Metadata-Version: 2.1
Name: flowgo
Version: 1.1
Summary: This module for creating and working with individual threads in the local memory of each.
Home-page: https://github.com/YesthisI/flow/
Author: YesthisI
Author-email: teiwaz-h@mail.ru
Keywords: stack,local,threaded
Classifier: Programming Language :: Python :: 3.8
Classifier: License :: OSI Approved :: MIT License
Classifier: Operating System :: OS Independent
License-File: LICENSE
